flake8_rst_docstrings.py
flake8_rst_docstrings-0.4.0.dist-info/licenses/LICENSE.rst
flake8_rst_docstrings-0.4.0.dist-info/METADATA
flake8_rst_docstrings-0.4.0.dist-info/WHEEL
flake8_rst_docstrings-0.4.0.dist-info/entry_points.txt
flake8_rst_docstrings-0.4.0.dist-info/top_level.txt
flake8_rst_docstrings-0.4.0.dist-info/zip-safe
flake8_rst_docstrings-0.4.0.dist-info/RECORD
